django_jquery_ui-1.11.4.1.dist-info/DESCRIPTION.rst
django_jquery_ui-1.11.4.1.dist-info/METADATA
django_jquery_ui-1.11.4.1.dist-info/RECORD
django_jquery_ui-1.11.4.1.dist-info/WHEEL
django_jquery_ui-1.11.4.1.dist-info/metadata.json
django_jquery_ui-1.11.4.1.dist-info/top_level.txt
jquery_ui/__init__.py
jquery_ui/models.py
jquery_ui/static/css/jquery-ui/black-tie/jquery-ui.css
jquery_ui/static/css/jquery-ui/black-tie/jquery-ui.min.css
jquery_ui/static/css/jquery-ui/black-tie/theme.css
jquery_ui/static/css/jquery-ui/black-tie/images/ui-bg_diagonals-thick_8_333333_40x40.png
jquery_ui/static/css/jquery-ui/black-tie/images/ui-bg_flat_65_ffffff_40x100.png
jquery_ui/static/css/jquery-ui/black-tie/images/ui-bg_glass_40_111111_1x400.png
jquery_ui/static/css/jquery-ui/black-tie/images/ui-bg_glass_55_1c1c1c_1x400.png
jquery_ui/static/css/jquery-ui/black-tie/images/ui-bg_highlight-hard_100_f9f9f9_1x100.png
jquery_ui/static/css/jquery-ui/black-tie/images/ui-bg_highlight-hard_40_aaaaaa_1x100.png
jquery_ui/static/css/jquery-ui/black-tie/images/ui-bg_highlight-soft_50_aaaaaa_1x100.png
jquery_ui/static/css/jquery-ui/black-tie/images/ui-bg_inset-hard_45_cd0a0a_1x100.png
jquery_ui/static/css/jquery-ui/black-tie/images/ui-bg_inset-hard_55_ffeb80_1x100.png
jquery_ui/static/css/jquery-ui/black-tie/images/ui-icons_222222_256x240.png
jquery_ui/static/css/jquery-ui/black-tie/images/ui-icons_4ca300_256x240.png
jquery_ui/static/css/jquery-ui/black-tie/images/ui-icons_bbbbbb_256x240.png
jquery_ui/static/css/jquery-ui/black-tie/images/ui-icons_ededed_256x240.png
jquery_ui/static/css/jquery-ui/black-tie/images/ui-icons_ffcf29_256x240.png
jquery_ui/static/css/jquery-ui/black-tie/images/ui-icons_ffffff_256x240.png
jquery_ui/static/css/jquery-ui/blitzer/jquery-ui.css
jquery_ui/static/css/jquery-ui/blitzer/jquery-ui.min.css
jquery_ui/static/css/jquery-ui/blitzer/theme.css
jquery_ui/static/css/jquery-ui/blitzer/images/ui-bg_diagonals-thick_75_f3d8d8_40x40.png
jquery_ui/static/css/jquery-ui/blitzer/images/ui-bg_dots-small_65_a6a6a6_2x2.png
jquery_ui/static/css/jquery-ui/blitzer/images/ui-bg_flat_0_333333_40x100.png
jquery_ui/static/css/jquery-ui/blitzer/images/ui-bg_flat_65_ffffff_40x100.png
