Metadata-Version: 2.0
Name: django-jquery-ui
Version: 1.11.4.1
Summary: jQuery UI packaged in a django app to speed up new applications and deployment.
Home-page: https://github.com/benbacardi/django-jquery-ui
Author: Ben Cardy
Author-email: benbacardi@gmail.com
License: MIT
Keywords: django,jquery,jqueryui,staticfiles
Platform: any
Classifier: Development Status :: 5 - Production/Stable
Classifier: Environment :: Web Environment
Classifier: Framework :: Django
Classifier: Intended Audience :: Developers
Classifier: Natural Language :: English
Classifier: License :: OSI Approved :: MIT License
Classifier: Operating System :: OS Independent
Classifier: Programming Language :: Python
Classifier: Topic :: Utilities
Requires-Dist: django-jquery (>=1.6)
